pipelinenotifier/__init__.py
pipelinenotifier/base.py
pipelinenotifier/discord.py
pipelinenotifier/keybase.py
pipelinenotifier/slack.py
jacky_tools-0.0.1.dist-info/LICENSE
jacky_tools-0.0.1.dist-info/METADATA
jacky_tools-0.0.1.dist-info/WHEEL
jacky_tools-0.0.1.dist-info/top_level.txt
jacky_tools-0.0.1.dist-info/RECORD
